MCcoordstore/__init__.py
MCcoordstore/api_poi.py
MCcoordstore/app.py
MCcoordstore/db.py
MCcoordstore/default_config.py
MCcoordstore/forms.py
MCcoordstore/login.py
MCcoordstore/plots.py
MCcoordstore/renderstyle_utils.py
MCcoordstore/serializers.py
MCcoordstore/utils.py
MCcoordstore/wsgi.py
MCcoordstore/static/scripts/plotly_render.js
MCcoordstore/static/scripts/table_utils.js
MCcoordstore/static/styles/style.css
MCcoordstore/static/styles/style.css~
MCcoordstore/templates/#index.htm#
MCcoordstore/templates/#navbar.htm#
MCcoordstore/templates/add_manual.htm
MCcoordstore/templates/add_manual.htm~
MCcoordstore/templates/base.htm
MCcoordstore/templates/base.htm~
MCcoordstore/templates/index.htm
MCcoordstore/templates/index.htm~
MCcoordstore/templates/index_old.htm
MCcoordstore/templates/login.htm
MCcoordstore/templates/login.htm~
MCcoordstore/templates/navbar.htm
MCcoordstore/templates/navbar.htm~
MCcoordstore/templates/plotly_render_test.htm
MCcoordstore/templates/signup.htm
MCcoordstore/templates/signup.htm~
MCcoordstore/templates/style.css
MCcoordstore/templates/style.css~
MCcoordstore/templates/style_edit.htm
MCcoordstore/templates/style_select.htm
MCcoordstore/templates/style_select.htm~
MCcoordstore-0.0.4.dev0.dist-info/LICENSE
MCcoordstore-0.0.4.dev0.dist-info/METADATA
MCcoordstore-0.0.4.dev0.dist-info/WHEEL
MCcoordstore-0.0.4.dev0.dist-info/top_level.txt
MCcoordstore-0.0.4.dev0.dist-info/RECORD
