Metadata-Version: 2.1
Name: MCcoordstore
Version: 0.0.4.dev0
Summary: simple coordinate store for minecraft
Home-page: https://github.com/weatherhead99/MCcoordstore
Author: Dan Weatherill
Author-email: dan.weatherill@cantab.net
License: AGPL-3.0-or-later
Platform: UNKNOWN
Classifier: Development Status :: 2 - Pre-Alpha
Classifier: Framework :: Flask
Classifier: License :: OSI Approved :: GNU Affero General Public License v3
Classifier: Topic :: Internet :: WWW/HTTP :: WSGI :: Application
License-File: LICENSE
Requires-Dist: flask
Requires-Dist: flask-sqlalchemy
Requires-Dist: Flask-WTF
Requires-Dist: Flask-login
Requires-Dist: matplotlib
Requires-Dist: numpy
Requires-Dist: mpld3
Requires-Dist: werkzeug
Requires-Dist: flask-migrate
Requires-Dist: itsdangerous
Requires-Dist: flask-restless-NG
Requires-Dist: pytz
Requires-Dist: python-dotenv
